odoo8_addon_base_optional_quick_create-8.0.0.1.0.99.dev23-py2.7-nspkg.pth
odoo8_addon_base_optional_quick_create-8.0.0.1.0.99.dev23.dist-info/DESCRIPTION.rst
odoo8_addon_base_optional_quick_create-8.0.0.1.0.99.dev23.dist-info/METADATA
odoo8_addon_base_optional_quick_create-8.0.0.1.0.99.dev23.dist-info/RECORD
odoo8_addon_base_optional_quick_create-8.0.0.1.0.99.dev23.dist-info/WHEEL
odoo8_addon_base_optional_quick_create-8.0.0.1.0.99.dev23.dist-info/metadata.json
odoo8_addon_base_optional_quick_create-8.0.0.1.0.99.dev23.dist-info/namespace_packages.txt
odoo8_addon_base_optional_quick_create-8.0.0.1.0.99.dev23.dist-info/top_level.txt
odoo_addons/base_optional_quick_create/AUTHORS.txt
odoo_addons/base_optional_quick_create/__init__.py
odoo_addons/base_optional_quick_create/__openerp__.py
odoo_addons/base_optional_quick_create/model.py
odoo_addons/base_optional_quick_create/model_view.xml
odoo_addons/base_optional_quick_create/i18n/base_optional_quick_create.pot
odoo_addons/base_optional_quick_create/i18n/ca.po
odoo_addons/base_optional_quick_create/i18n/de.po
odoo_addons/base_optional_quick_create/i18n/es.po
odoo_addons/base_optional_quick_create/i18n/es_ES.po
odoo_addons/base_optional_quick_create/i18n/eu.po
odoo_addons/base_optional_quick_create/i18n/fi.po
odoo_addons/base_optional_quick_create/i18n/fr.po
odoo_addons/base_optional_quick_create/i18n/hr.po
odoo_addons/base_optional_quick_create/i18n/hr_HR.po
odoo_addons/base_optional_quick_create/i18n/it.po
odoo_addons/base_optional_quick_create/i18n/nl.po
odoo_addons/base_optional_quick_create/i18n/pt_BR.po
odoo_addons/base_optional_quick_create/i18n/pt_PT.po
odoo_addons/base_optional_quick_create/i18n/sl.po
odoo_addons/base_optional_quick_create/i18n/tr.po
odoo_addons/base_optional_quick_create/i18n/tr_TR.po
odoo_addons/base_optional_quick_create/static/description/icon.png
