Metadata-Version: 2.0
Name: odoo8-addon-base-optional-quick-create
Version: 8.0.0.1.0.99.dev23
Summary: Avoid 'quick create' on m2o fields, on a 'by model' basis
Home-page: http://www.agilebg.com
Author: Agile Business Group,Odoo Community Association (OCA)
Author-email: support@odoo-community.org
License: AGPL-3
Platform: UNKNOWN
Classifier: Programming Language :: Python
Classifier: Framework :: Odoo
Classifier: License :: OSI Approved :: GNU Affero General Public License v3
Requires-Python: ~=2.7
Requires-Dist: odoo (<9.0a,>=8.0a)
